[
  { "name": "Electro Hypostasis", "type": "boss", "region": "Mondstadt", "compliant": "yes" },
  { "name": "Anemo Hypostasis", "type": "boss", "region": "Mondstadt", "compliant": "yes" },
  { "name": "Cryo Regisvine", "type": "boss", "region": "Mondstadt", "compliant": "yes" },
  { "name": "Geo Hypostasis", "type": "boss", "region": "Liyue", "compliant": "yes" },
  { "name": "Oceanid", "type": "boss", "region": "Liyue", "compliant": "yes" },
  { "name": "Pyro Regisvine", "type": "boss", "region": "Liyue", "compliant": "yes" },
  { "name": "Primo Geovishap", "type": "boss", "region": "Liyue", "compliant": "yes" },
  { "name": "Cryo Hypostasis", "type": "boss", "region": "Mondstadt", "compliant": "yes" },
  { "name": "Maguu Kenki", "type": "boss", "region": "Inazuma", "compliant": "yes" },
  { "name": "Pyro Hypostasis", "type": "boss", "region": "Inazuma", "compliant": "yes" },
  { "name": "Perpetual Mechanical Array", "type": "boss", "region": "Inazuma", "compliant": "yes" },
  { "name": "Hydro Hypostasis", "type": "boss", "region": "Inazuma", "compliant": "yes" },
  { "name": "Thunder Manifestation", "type": "boss", "region": "Inazuma", "compliant": "yes" },
  { "name": "Golden Wolflord", "type": "boss", "region": "Inazuma", "compliant": "yes" },
  { "name": "Bathysmal Vishap Herd", "type": "boss", "region": "Inazuma", "compliant": "yes" },
  { "name": "Ruin Serpent", "type": "boss", "region": "Liyue", "compliant": "yes" },
  { "name": "Electro Regisvine", "type": "boss", "region": "Sumeru", "compliant": "yes" },
  { "name": "Jadeplume Terrorshroom", "type": "boss", "region": "Sumeru", "compliant": "yes" },
  { "name": "Aeonblight Drake", "type": "boss", "region": "Sumeru", "compliant": "yes" },
  { "name": "ASIMON", "type": "boss", "region": "Sumeru", "compliant": "yes" },
  { "name": "Dendro Hypostasis", "type": "boss", "region": "Sumeru", "compliant": "yes" },
  { "name": "Setekh Wenut", "type": "boss", "region": "Sumeru", "compliant": "yes" },
  { "name": "Algorithm of Semi-Intransient Matrix", "type": "boss", "region": "Sumeru", "compliant": "yes" },
  { "name": "Icewind Suite", "type": "boss", "region": "Fontaine", "compliant": "yes" },
  { "name": "Emperor of Fire and Iron", "type": "boss", "region": "Fontaine", "compliant": "yes" },
  { "name": "Experimental Field Generator", "type": "boss", "region": "Fontaine", "compliant": "yes" },
  { "name": "Millennial Pearl Seahorse", "type": "boss", "region": "Fontaine", "compliant": "yes" },
  { "name": "Hydro Tulpa", "type": "boss", "region": "Fontaine", "compliant": "yes" },
  { "name": "Suanni", "type": "boss", "region": "Liyue", "compliant": "yes" },
  { "name": "Legatus Golem", "type": "boss", "region": "Fontaine", "compliant": "yes" },

  { "name": "Gluttonous Yumkasaur", "type": "boss", "region": "Natlan", "compliant": "yes" },
  { "name": "Goldflame Quacusaur", "type": "boss", "region": "Natlan", "compliant": "yes" },
  { "name": "SSA Configuration Device", "type": "boss", "region": "Natlan", "compliant": "yes" },
  { "name": "Papilla", "type": "boss", "region": "Natlan", "compliant": "yes" },
  { "name": "Wayward Spiritspeaker", "type": "boss", "region": "Natlan", "compliant": "yes" },
  { "name": "Lava Dragon Statue", "type": "boss", "region": "Natlan", "compliant": "yes" },
  { "name": "SSA Overseer Device", "type": "boss", "region": "Natlan", "compliant": "yes" },

  { "name": "Knuckle Duckle", "type": "boss", "region": "Nodkrai", "compliant": "yes" },
  { "name": "Radiant Moonfly", "type": "boss", "region": "Nodkrai", "compliant": "yes" },
  { "name": "Frostnight Herra", "type": "boss", "region": "Nodkrai", "compliant": "yes" },
  { "name": "Super-Heavy Landrover: Mechanized Fortress", "type": "boss", "region": "Nodkrai", "compliant": "yes" },
  { "name": "Lord of the Hidden Depths - Whisperer of Nightmares", "type": "boss", "region": "Nodkrai", "compliant": "yes" },

  { "name": "Lupus Boreas", "type": "weekly", "region": "Mondstadt", "compliant": "yes" },
  { "name": "Childe", "type": "weekly", "region": "Liyue", "compliant": "yes" },
  { "name": "Azhdaha", "type": "weekly", "region": "Liyue", "compliant": "yes" },
  { "name": "La Signora", "type": "weekly", "region": "Inazuma", "compliant": "yes" },
  { "name": "Raiden Shogun Puppet", "type": "weekly", "region": "Inazuma", "compliant": "yes" },
  { "name": "Scaramouche", "type": "weekly", "region": "Sumeru", "compliant": "yes" },
  { "name": "Apep", "type": "weekly", "region": "Sumeru", "compliant": "yes" },
  { "name": "All-Devouring Narwhal", "type": "weekly", "region": "Fontaine", "compliant": "yes" },
  { "name": "The Knave", "type": "weekly", "region": "Fontaine", "compliant": "yes" },
  { "name": "Eroded Primal Fire", "type": "weekly", "region": "Natlan", "compliant": "yes" },
  { "name": "Eternal Annihilator 'Chess Set'", "type": "weekly", "region": "Mondstadt", "compliant": "yes" },
  { "name": "The Doctor - Dottore", "type": "weekly", "region": "Nodkrai", "compliant": "yes" },

  { "name": "Ruler of the Chizhang Mountains", "type": "local legend", "region": "Liyue", "compliant": "yes" },

  { "name": "Cineas", "type": "local legend", "region": "Fontaine", "compliant": "yes" },
  { "name": "Deianeira of Snezhevna", "type": "local legend", "region": "Fontaine", "compliant": "yes" },
  { "name": "Chassanion", "type": "local legend", "region": "Fontaine", "compliant": "no" },
  { "name": "Mageblade Corrouge", "type": "local legend", "region": "Fontaine", "compliant": "no" },
  { "name": "Rocky Avildsen", "type": "local legend", "region": "Fontaine", "compliant": "yes" },
  { "name": "Liam", "type": "local legend", "region": "Fontaine", "compliant": "yes" },
  { "name": "Automated Supercomputing Field Generator", "type": "local legend", "region": "Fontaine", "compliant": "yes" },
  { "name": "Luachra the Brilliant", "type": "local legend", "region": "Fontaine", "compliant": "no" },
  { "name": "Yseut", "type": "local legend", "region": "Fontaine", "compliant": "yes" },
  { "name": "Fading Veteran", "type": "local legend", "region": "Fontaine", "compliant": "no" },
  { "name": "Fairy Knight Twins", "type": "local legend", "region": "Fontaine", "compliant": "no" },
  { "name": "Swords of the Gorge", "type": "local legend", "region": "Fontaine", "compliant": "no" },
  { "name": "Dobharcu, Lord of the Hidden", "type": "local legend", "region": "Fontaine", "compliant": "no" },
  { "name": "Ninianne of the Lake", "type": "local legend", "region": "Fontaine", "compliant": "yes" },
  { "name": "Vivianne of the Lake", "type": "local legend", "region": "Fontaine", "compliant": "yes" },

  { "name": "The Last Survivor of Tenochtzitoc", "type": "local legend", "region": "Natlan", "compliant": "yes" },
  { "name": "Infinitesimal", "type": "local legend", "region": "Natlan", "compliant": "yes" },
  { "name": "The Peak", "type": "local legend", "region": "Natlan", "compliant": "yes" },
  { "name": "Ironclaw and Battlegoat", "type": "local legend", "region": "Natlan", "compliant": "yes" },
  { "name": "Reji", "type": "local legend", "region": "Natlan", "compliant": "no" },
  { "name": "Tupu's Lushness", "type": "local legend", "region": "Natlan", "compliant": "no" },
  { "name": "Tupayo's Aid", "type": "local legend", "region": "Natlan", "compliant": "no" },
  { "name": "Tlatzacuilotl", "type": "local legend", "region": "Natlan", "compliant": "no" },
  { "name": "Spirit of the Fallen Dawnstar", "type": "local legend", "region": "Natlan", "compliant": "no" },
  { "name": "Sappho Amidst The Waves", "type": "local legend", "region": "Natlan", "compliant": "yes" },
  { "name": "Rilai", "type": "local legend", "region": "Natlan", "compliant": "yes" },
  { "name": "Potapo's Solidarity", "type": "local legend", "region": "Natlan", "compliant": "no" },
  { "name": "Polychrome Tri-Stars", "type": "local legend", "region": "Natlan", "compliant": "yes" },
  { "name": "Ironbeard", "type": "local legend", "region": "Natlan", "compliant": "no" },
  { "name": "Ichcahuipilli's Aegis", "type": "local legend", "region": "Natlan", "compliant": "no" },
  { "name": "He Never Dies", "type": "local legend", "region": "Natlan", "compliant": "no" },
  { "name": "Cocijo", "type": "local legend", "region": "Natlan", "compliant": "yes" },
  { "name": "Cihuacoatl of Chimeric Bone", "type": "local legend", "region": "Natlan", "compliant": "no" },
  { "name": "Chimalli's Shade", "type": "local legend", "region": "Natlan", "compliant": "no" },
  { "name": "Bronzelock", "type": "local legend", "region": "Natlan", "compliant": "yes" },
  { "name": "Balachko", "type": "local legend", "region": "Natlan", "compliant": "yes" },
  { "name": "Atlatl's Blessing", "type": "local legend", "region": "Natlan", "compliant": "no" },

  { "name": "Raskolnikov", "type": "local legend", "region": "Nodkrai", "compliant": "yes" },
  { "name": "Crab Tsar", "type": "local legend", "region": "Nodkrai", "compliant": "yes" },
  { "name": "Sigurd", "type": "local legend", "region": "Nodkrai", "compliant": "yes" },
  { "name": "Hexadecatonic Mandragora", "type": "local legend", "region": "Nodkrai", "compliant": "yes" },
  { "name": "Hiljetta", "type": "local legend", "region": "Nodkrai", "compliant": "yes" },
  { "name": "The Homesick Lone Wolf", "type": "local legend", "region": "Nodkrai", "compliant": "yes" },
  { "name": "Radiant Moongecko", "type": "boss", "region": "Nodkrai", "compliant": "yes" }
]